{
    "orgRecordClass": "RC1",
    "Name": "FAIRVIEW PHARMACY LIMITED",
    "Date": {
        "Type": {
            "value": "Operational"
        },
        "Start": {
            "value": "2012-07-01"
        }
    },
    "OrgId": {
        "root": "2.16.840.1.113883.2.1.3.2.4.18.48",
        "assigningAuthorityName": "HSCIC",
        "extension": "P1R7"
    },
    "Status": {
        "value": "Active"
    },
    "LastChangeDate": {
        "value": "2012-08-01"
    },
    "GeoLoc": {
        "Location": {
            "AddrLn1": "FAIRVIEW PHARMACY",
            "AddrLn2": "293-295 BURNT OAK BROADWAY",
            "Town": "EDGWARE",
            "County": "MIDDLESEX",
            "PostCode": "HA8 5ED",
            "Country": "ENGLAND"
        }
    },
    "Roles": {
        "Role": {
            "id": "RO181",
            "uniqueRoleId": "162885",
            "primaryRole": "true",
            "Date": {
                "Type": {
                    "value": "Operational"
                },
                "Start": {
                    "value": "2012-07-01"
                }
            },
            "Status": {
                "value": "Active"
            }
        }
    },
    "metadata": {
        "org_id": "P1R7",
        "status": "Active",
        "role_id": "RO181"
    }
}