{
    "orgRecordClass": "RC2",
    "Name": "MORRAB COTTAGE",
    "Date": {
        "Type": {
            "value": "Operational"
        },
        "Start": {
            "value": "2006-04-01"
        }
    },
    "OrgId": {
        "root": "2.16.840.1.113883.2.1.3.2.4.18.48",
        "assigningAuthorityName": "HSCIC",
        "extension": "RJ8CR"
    },
    "Status": {
        "value": "Active"
    },
    "LastChangeDate": {
        "value": "2021-02-04"
    },
    "GeoLoc": {
        "Location": {
            "AddrLn1": "MORRAB GARDENS",
            "Town": "PENZANCE",
            "County": "CORNWALL",
            "PostCode": "TR18 4DA",
            "Country": "ENGLAND",
            "UPRN": "10023469335"
        }
    },
    "Roles": {
        "Role": {
            "id": "RO198",
            "uniqueRoleId": "25969",
            "primaryRole": "true",
            "Date": {
                "Type": {
                    "value": "Operational"
                },
                "Start": {
                    "value": "2006-04-01"
                }
            },
            "Status": {
                "value": "Active"
            }
        }
    },
    "Rels": {
        "Rel": {
            "id": "RE6",
            "uniqueRelId": "51681",
            "Date": {
                "Type": {
                    "value": "Operational"
                },
                "Start": {
                    "value": "2006-04-01"
                }
            },
            "Status": {
                "value": "Active"
            },
            "Target": {
                "OrgId": {
                    "root": "2.16.840.1.113883.2.1.3.2.4.18.48",
                    "assigningAuthorityName": "HSCIC",
                    "extension": "RJ8"
                },
                "PrimaryRoleId": {
                    "id": "RO197",
                    "uniqueRoleId": "48404"
                }
            }
        }
    },
    "metadata": {
        "org_id": "RJ8CR",
        "status": "Active",
        "role_id": "RO198"
    }
}