{
    "orgRecordClass": "RC2",
    "Name": "LAMBETH D & A TEAM",
    "Date": {
        "Type": {
            "value": "Operational"
        },
        "Start": {
            "value": "2004-04-01"
        }
    },
    "OrgId": {
        "root": "2.16.840.1.113883.2.1.3.2.4.18.48",
        "assigningAuthorityName": "HSCIC",
        "extension": "RV527"
    },
    "Status": {
        "value": "Active"
    },
    "LastChangeDate": {
        "value": "2024-04-02"
    },
    "GeoLoc": {
        "Location": {
            "AddrLn1": "LORRAINE HEWITT HOUSE",
            "AddrLn2": "12-14 BRIGHTON TERRACE",
            "Town": "LONDON",
            "PostCode": "SW9 8DG",
            "Country": "ENGLAND",
            "UPRN": "10008790584"
        }
    },
    "Roles": {
        "Role": [
            {
                "id": "RO31",
                "uniqueRoleId": "158125",
                "Date": {
                    "Type": {
                        "value": "Operational"
                    },
                    "Start": {
                        "value": "2007-10-01"
                    }
                },
                "Status": {
                    "value": "Active"
                }
            },
            {
                "id": "RO198",
                "uniqueRoleId": "109034",
                "primaryRole": "true",
                "Date": {
                    "Type": {
                        "value": "Operational"
                    },
                    "Start": {
                        "value": "2004-04-01"
                    }
                },
                "Status": {
                    "value": "Active"
                }
            }
        ]
    },
    "Rels": {
        "Rel": {
            "id": "RE6",
            "uniqueRelId": "75949",
            "Date": {
                "Type": {
                    "value": "Operational"
                },
                "Start": {
                    "value": "2004-04-01"
                }
            },
            "Status": {
                "value": "Active"
            },
            "Target": {
                "OrgId": {
                    "root": "2.16.840.1.113883.2.1.3.2.4.18.48",
                    "assigningAuthorityName": "HSCIC",
                    "extension": "RV5"
                },
                "PrimaryRoleId": {
                    "id": "RO197",
                    "uniqueRoleId": "118522"
                }
            }
        }
    },
    "metadata": {
        "org_id": "RV527",
        "status": "Active",
        "role_id": "RO198",
        "post_code": "SW9 8DG",
        "uprn": "10008790584"
    }
}