{
    "orgRecordClass": "RC2",
    "Name": "WELLESBOURNE CAS-CP",
    "Date": {
        "Type": {
            "value": "Operational"
        },
        "Start": {
            "value": "2012-10-01"
        }
    },
    "OrgId": {
        "root": "2.16.840.1.113883.2.1.3.2.4.18.48",
        "assigningAuthorityName": "HSCIC",
        "extension": "RYAE7"
    },
    "Status": {
        "value": "Active"
    },
    "LastChangeDate": {
        "value": "2021-07-21"
    },
    "GeoLoc": {
        "Location": {
            "AddrLn1": "WELLESBOURNE AIRFIELD",
            "AddrLn2": "LOXLEY ROAD",
            "AddrLn3": "WELLESBOURNE",
            "Town": "WARWICK",
            "County": "WARWICKSHIRE",
            "PostCode": "CV35 9EU",
            "Country": "ENGLAND",
            "UPRN": "10023388801"
        }
    },
    "Roles": {
        "Role": {
            "id": "RO198",
            "uniqueRoleId": "165535",
            "primaryRole": "true",
            "Date": {
                "Type": {
                    "value": "Operational"
                },
                "Start": {
                    "value": "2012-10-01"
                }
            },
            "Status": {
                "value": "Active"
            }
        }
    },
    "Rels": {
        "Rel": {
            "id": "RE6",
            "uniqueRelId": "188472",
            "Date": {
                "Type": {
                    "value": "Operational"
                },
                "Start": {
                    "value": "2012-10-01"
                }
            },
            "Status": {
                "value": "Active"
            },
            "Target": {
                "OrgId": {
                    "root": "2.16.840.1.113883.2.1.3.2.4.18.48",
                    "assigningAuthorityName": "HSCIC",
                    "extension": "RYA"
                },
                "PrimaryRoleId": {
                    "id": "RO197",
                    "uniqueRoleId": "97369"
                }
            }
        }
    },
    "metadata": {
        "org_id": "RYAE7",
        "status": "Active",
        "role_id": "RO198"
    }
}