{
    "orgRecordClass": "RC2",
    "Name": "SOUTHAMPTON LOGISTICS & PHARMACY UNIT",
    "Date": {
        "Type": {
            "value": "Operational"
        },
        "Start": {
            "value": "2022-10-01"
        }
    },
    "OrgId": {
        "root": "2.16.840.1.113883.2.1.3.2.4.18.48",
        "assigningAuthorityName": "HSCIC",
        "extension": "O6U7V"
    },
    "Status": {
        "value": "Active"
    },
    "LastChangeDate": {
        "value": "2024-07-30"
    },
    "GeoLoc": {
        "Location": {
            "AddrLn1": "UNIT H3",
            "AddrLn2": "ADNAC NORTH",
            "Town": "SOUTHAMPTON",
            "County": "HAMPSHIRE",
            "PostCode": "SO16 0BT",
            "Country": "ENGLAND"
        }
    },
    "Roles": {
        "Role": [
            {
                "id": "RO198",
                "uniqueRoleId": "499137",
                "primaryRole": "true",
                "Date": {
                    "Type": {
                        "value": "Operational"
                    },
                    "Start": {
                        "value": "2022-10-01"
                    }
                },
                "Status": {
                    "value": "Active"
                }
            }
        ]
    },
    "Rels": {
        "Rel": {
            "id": "RE6",
            "uniqueRelId": "820847",
            "Date": {
                "Type": {
                    "value": "Operational"
                },
                "Start": {
                    "value": "2022-10-01"
                }
            },
            "Status": {
                "value": "Active"
            },
            "Target": {
                "OrgId": {
                    "root": "2.16.840.1.113883.2.1.3.2.4.18.48",
                    "assigningAuthorityName": "HSCIC",
                    "extension": "RYE"
                },
                "PrimaryRoleId": {
                    "id": "RO197",
                    "uniqueRoleId": "78378"
                }
            }
        }
    },
    "metadata": {
        "org_id": "O6U7V",
        "status": "Active",
        "role_id": "RO198",
        "post_code": "SO16 0BT",
        "uprn": "Unknown"
    }
}