{
    "orgRecordClass": "RC2",
    "Name": "CARTERTON LEISURE CENTRE",
    "Date": {
        "Type": {
            "value": "Operational"
        },
        "Start": {
            "value": "2024-06-04"
        }
    },
    "OrgId": {
        "root": "2.16.840.1.113883.2.1.3.2.4.18.48",
        "assigningAuthorityName": "HSCIC",
        "extension": "W6B2H"
    },
    "Status": {
        "value": "Active"
    },
    "LastChangeDate": {
        "value": "2024-06-04"
    },
    "GeoLoc": {
        "Location": {
            "AddrLn1": "BROADSHIRES WAY",
            "Town": "CARTERTON",
            "PostCode": "OX18 1AA",
            "Country": "ENGLAND",
            "UPRN": "10002187931"
        }
    },
    "Roles": {
        "Role": [
            {
                "id": "RO198",
                "uniqueRoleId": "526360",
                "primaryRole": "true",
                "Date": {
                    "Type": {
                        "value": "Operational"
                    },
                    "Start": {
                        "value": "2024-06-04"
                    }
                },
                "Status": {
                    "value": "Active"
                }
            }
        ]
    },
    "Rels": {
        "Rel": {
            "id": "RE6",
            "uniqueRelId": "847359",
            "Date": {
                "Type": {
                    "value": "Operational"
                },
                "Start": {
                    "value": "2024-06-04"
                }
            },
            "Status": {
                "value": "Active"
            },
            "Target": {
                "OrgId": {
                    "root": "2.16.840.1.113883.2.1.3.2.4.18.48",
                    "assigningAuthorityName": "HSCIC",
                    "extension": "RTH"
                },
                "PrimaryRoleId": {
                    "id": "RO197",
                    "uniqueRoleId": "128477"
                }
            }
        }
    },
    "metadata": {
        "org_id": "W6B2H",
        "status": "Active",
        "role_id": "RO198",
        "post_code": "OX18 1AA",
        "uprn": "10002187931"
    }
}