{
    "orgRecordClass": "RC1",
    "Name": "TY MAWR",
    "Date": {
        "Type": {
            "value": "Operational"
        },
        "Start": {
            "value": "2019-06-12"
        }
    },
    "OrgId": {
        "root": "2.16.840.1.113883.2.1.3.2.4.18.48",
        "assigningAuthorityName": "HSCIC",
        "extension": "VM6YP"
    },
    "Status": {
        "value": "Active"
    },
    "LastChangeDate": {
        "value": "2019-08-13"
    },
    "GeoLoc": {
        "Location": {
            "AddrLn1": "LONGFORD COURT",
            "Town": "NEATH",
            "PostCode": "SA10 7HN",
            "Country": "WALES",
            "UPRN": "10009180484"
        }
    },
    "Roles": {
        "Role": [
            {
                "id": "RO101",
                "uniqueRoleId": "382951",
                "primaryRole": "true",
                "Date": {
                    "Type": {
                        "value": "Operational"
                    },
                    "Start": {
                        "value": "2019-06-12"
                    }
                },
                "Status": {
                    "value": "Active"
                }
            },
            {
                "id": "RO269",
                "uniqueRoleId": "382952",
                "Date": {
                    "Type": {
                        "value": "Operational"
                    },
                    "Start": {
                        "value": "2019-06-12"
                    }
                },
                "Status": {
                    "value": "Active"
                }
            }
        ]
    },
    "Rels": {
        "Rel": [
            {
                "id": "RE5",
                "uniqueRelId": "604921",
                "Date": {
                    "Type": {
                        "value": "Operational"
                    },
                    "Start": {
                        "value": "2019-06-12"
                    }
                },
                "Status": {
                    "value": "Active"
                },
                "Target": {
                    "OrgId": {
                        "root": "2.16.840.1.113883.2.1.3.2.4.18.48",
                        "assigningAuthorityName": "HSCIC",
                        "extension": "7A3"
                    },
                    "PrimaryRoleId": {
                        "id": "RO142",
                        "uniqueRoleId": "40383"
                    }
                }
            },
            {
                "id": "RE6",
                "uniqueRelId": "604922",
                "Date": {
                    "Type": {
                        "value": "Operational"
                    },
                    "Start": {
                        "value": "2019-06-12"
                    }
                },
                "Status": {
                    "value": "Active"
                },
                "Target": {
                    "OrgId": {
                        "root": "2.16.840.1.113883.2.1.3.2.4.18.48",
                        "assigningAuthorityName": "HSCIC",
                        "extension": "AH8Y"
                    },
                    "PrimaryRoleId": {
                        "id": "RO104",
                        "uniqueRoleId": "382745"
                    }
                }
            }
        ]
    },
    "metadata": {
        "org_id": "VM6YP",
        "status": "Active",
        "role_id": "RO101"
    }
}