{
    "orgRecordClass": "RC1",
    "Name": "HULL HOMECARE",
    "Date": {
        "Type": {
            "value": "Operational"
        },
        "Start": {
            "value": "2016-05-13"
        }
    },
    "OrgId": {
        "root": "2.16.840.1.113883.2.1.3.2.4.18.48",
        "assigningAuthorityName": "HSCIC",
        "extension": "VN97C"
    },
    "Status": {
        "value": "Active"
    },
    "LastChangeDate": {
        "value": "2020-06-02"
    },
    "GeoLoc": {
        "Location": {
            "AddrLn1": "17 PRESTONGATE",
            "Town": "HESSLE",
            "PostCode": "HU13 0RD",
            "Country": "ENGLAND",
            "UPRN": "10002828550"
        }
    },
    "Roles": {
        "Role": [
            {
                "id": "RO101",
                "uniqueRoleId": "372103",
                "primaryRole": "true",
                "Date": {
                    "Type": {
                        "value": "Operational"
                    },
                    "Start": {
                        "value": "2016-05-13"
                    }
                },
                "Status": {
                    "value": "Active"
                }
            },
            {
                "id": "RO270",
                "uniqueRoleId": "372104",
                "Date": {
                    "Type": {
                        "value": "Operational"
                    },
                    "Start": {
                        "value": "2016-05-13"
                    }
                },
                "Status": {
                    "value": "Active"
                }
            }
        ]
    },
    "Rels": {
        "Rel": [
            {
                "id": "RE5",
                "uniqueRelId": "589707",
                "Date": {
                    "Type": {
                        "value": "Operational"
                    },
                    "Start": {
                        "value": "2016-05-13"
                    }
                },
                "Status": {
                    "value": "Active"
                },
                "Target": {
                    "OrgId": {
                        "root": "2.16.840.1.113883.2.1.3.2.4.18.48",
                        "assigningAuthorityName": "HSCIC",
                        "extension": "02Y"
                    },
                    "PrimaryRoleId": {
                        "id": "RO98",
                        "uniqueRoleId": "161462"
                    }
                }
            },
            {
                "id": "RE6",
                "uniqueRelId": "589708",
                "Date": {
                    "Type": {
                        "value": "Operational"
                    },
                    "Start": {
                        "value": "2016-05-13"
                    }
                },
                "Status": {
                    "value": "Active"
                },
                "Target": {
                    "OrgId": {
                        "root": "2.16.840.1.113883.2.1.3.2.4.18.48",
                        "assigningAuthorityName": "HSCIC",
                        "extension": "AXAX"
                    },
                    "PrimaryRoleId": {
                        "id": "RO104",
                        "uniqueRoleId": "353703"
                    }
                }
            }
        ]
    },
    "metadata": {
        "org_id": "VN97C",
        "status": "Active",
        "role_id": "RO101"
    }
}