{
    "orgRecordClass": "RC2",
    "Name": "GWENDOLEN HOUSE (TRUST HQ)",
    "Date": {
        "Type": {
            "value": "Operational"
        },
        "Start": {
            "value": "2004-04-01"
        },
        "End": {
            "value": "2017-04-30"
        }
    },
    "OrgId": {
        "root": "2.16.840.1.113883.2.1.3.2.4.18.48",
        "assigningAuthorityName": "HSCIC",
        "extension": "RWEHQ"
    },
    "Status": {
        "value": "Inactive"
    },
    "LastChangeDate": {
        "value": "2017-05-15"
    },
    "GeoLoc": {
        "Location": {
            "AddrLn1": "UNI HOSPITALS OF LEICS NHS TRUST",
            "AddrLn2": "GWENDOLEN ROAD",
            "Town": "LEICESTER",
            "County": "LEICESTERSHIRE",
            "PostCode": "LE5 4QF",
            "Country": "ENGLAND"
        }
    },
    "Contacts": {
        "Contact": {
            "type": "tel",
            "value": "0116 249 0490"
        }
    },
    "Roles": {
        "Role": {
            "id": "RO198",
            "uniqueRoleId": "68041",
            "primaryRole": "true",
            "Date": {
                "Type": {
                    "value": "Operational"
                },
                "Start": {
                    "value": "2004-04-01"
                },
                "End": {
                    "value": "2017-04-30"
                }
            },
            "Status": {
                "value": "Inactive"
            }
        }
    },
    "Rels": {
        "Rel": {
            "id": "RE6",
            "uniqueRelId": "60955",
            "Date": {
                "Type": {
                    "value": "Operational"
                },
                "Start": {
                    "value": "2004-04-01"
                },
                "End": {
                    "value": "2017-04-30"
                }
            },
            "Status": {
                "value": "Inactive"
            },
            "Target": {
                "OrgId": {
                    "root": "2.16.840.1.113883.2.1.3.2.4.18.48",
                    "assigningAuthorityName": "HSCIC",
                    "extension": "RWE"
                },
                "PrimaryRoleId": {
                    "id": "RO197",
                    "uniqueRoleId": "70438"
                }
            }
        }
    },
    "metadata": {
        "org_id": "RWEHQ",
        "status": "Inactive",
        "role_id": "RO198"
    }
}