{
    "orgRecordClass": "RC2",
    "Name": "LINDSEY LODGE",
    "Date": {
        "Type": {
            "value": "Operational"
        },
        "Start": {
            "value": "2015-04-01"
        }
    },
    "OrgId": {
        "root": "2.16.840.1.113883.2.1.3.2.4.18.48",
        "assigningAuthorityName": "HSCIC",
        "extension": "03KAC"
    },
    "Status": {
        "value": "Active"
    },
    "LastChangeDate": {
        "value": "2015-07-15"
    },
    "GeoLoc": {
        "Location": {
            "AddrLn1": "BURRINGHAM ROAD",
            "Town": "SCUNTHORPE",
            "County": "SOUTH HUMBERSIDE",
            "PostCode": "DN17 2AA",
            "Country": "ENGLAND"
        }
    },
    "Roles": {
        "Role": [
            {
                "id": "RO99",
                "uniqueRoleId": "233221",
                "primaryRole": "true",
                "Date": {
                    "Type": {
                        "value": "Operational"
                    },
                    "Start": {
                        "value": "2015-04-01"
                    }
                },
                "Status": {
                    "value": "Active"
                }
            }
        ]
    },
    "Rels": {
        "Rel": {
            "id": "RE6",
            "uniqueRelId": "385286",
            "Date": {
                "Type": {
                    "value": "Operational"
                },
                "Start": {
                    "value": "2015-04-01"
                }
            },
            "Status": {
                "value": "Active"
            },
            "Target": {
                "OrgId": {
                    "root": "2.16.840.1.113883.2.1.3.2.4.18.48",
                    "assigningAuthorityName": "HSCIC",
                    "extension": "03K"
                },
                "PrimaryRoleId": {
                    "id": "RO98",
                    "uniqueRoleId": "161473"
                }
            }
        }
    },
    "metadata": {
        "org_id": "03KAC",
        "status": "Active",
        "role_id": "RO99",
        "post_code": "DN17 2AA",
        "uprn": "Unknown"
    }
}