{
    "orgRecordClass": "RC1",
    "Name": "KING'S LEADERSHIP ACADEMY WARRINGTON",
    "Date": {
        "Type": {
            "value": "Operational"
        },
        "Start": {
            "value": "2012-09-01"
        }
    },
    "OrgId": {
        "root": "2.16.840.1.113883.2.1.3.2.4.18.48",
        "assigningAuthorityName": "HSCIC",
        "extension": "EE138562"
    },
    "Status": {
        "value": "Active"
    },
    "LastChangeDate": {
        "value": "2023-01-27"
    },
    "GeoLoc": {
        "Location": {
            "AddrLn1": "HILLOCK LANE",
            "AddrLn2": "WOOLSTON",
            "Town": "WARRINGTON",
            "PostCode": "WA1 4PF",
            "Country": "ENGLAND",
            "UPRN": "10092997137"
        }
    },
    "Contacts": {
        "Contact": {
            "type": "tel",
            "value": "01925 817939"
        }
    },
    "Roles": {
        "Role": [
            {
                "id": "RO221",
                "uniqueRoleId": "447510",
                "primaryRole": "true",
                "Date": {
                    "Type": {
                        "value": "Operational"
                    },
                    "Start": {
                        "value": "2012-09-01"
                    }
                },
                "Status": {
                    "value": "Active"
                }
            },
            {
                "id": "RO303",
                "uniqueRoleId": "447511",
                "Date": {
                    "Type": {
                        "value": "Operational"
                    },
                    "Start": {
                        "value": "2012-09-01"
                    }
                },
                "Status": {
                    "value": "Active"
                }
            }
        ]
    },
    "Rels": {
        "Rel": [
            {
                "id": "RE5",
                "uniqueRelId": "771581",
                "Date": {
                    "Type": {
                        "value": "Operational"
                    },
                    "Start": {
                        "value": "2012-09-01"
                    }
                },
                "Status": {
                    "value": "Active"
                },
                "Target": {
                    "OrgId": {
                        "root": "2.16.840.1.113883.2.1.3.2.4.18.48",
                        "assigningAuthorityName": "HSCIC",
                        "extension": "322"
                    },
                    "PrimaryRoleId": {
                        "id": "RO141",
                        "uniqueRoleId": "77602"
                    }
                }
            },
            {
                "id": "RE5",
                "uniqueRelId": "771580",
                "Date": [
                    {
                        "Type": {
                            "value": "Legal"
                        },
                        "Start": {
                            "value": "2013-04-01"
                        }
                    },
                    {
                        "Type": {
                            "value": "Operational"
                        },
                        "Start": {
                            "value": "2012-09-01"
                        }
                    }
                ],
                "Status": {
                    "value": "Active"
                },
                "Target": {
                    "OrgId": {
                        "root": "2.16.840.1.113883.2.1.3.2.4.18.48",
                        "assigningAuthorityName": "HSCIC",
                        "extension": "02E"
                    },
                    "PrimaryRoleId": {
                        "id": "RO98",
                        "uniqueRoleId": "161447"
                    }
                }
            }
        ]
    },
    "metadata": {
        "org_id": "EE138562",
        "status": "Active",
        "role_id": "RO221",
        "post_code": "WA1 4PF",
        "uprn": "10092997137"
    }
}