{
    "orgRecordClass": "RC2",
    "Name": "STAFFORDSHIRE COUNTY COUNCIL - PUBLIC HEALTH TEAM",
    "Date": {
        "Type": {
            "value": "Operational"
        },
        "Start": {
            "value": "2015-04-01"
        }
    },
    "OrgId": {
        "root": "2.16.840.1.113883.2.1.3.2.4.18.48",
        "assigningAuthorityName": "HSCIC",
        "extension": "413AA"
    },
    "Status": {
        "value": "Active"
    },
    "LastChangeDate": {
        "value": "2015-09-22"
    },
    "GeoLoc": {
        "Location": {
            "AddrLn1": "1 STAFFORDSHIRE PLACE",
            "Town": "STAFFORD",
            "County": "STAFFORDSHIRE",
            "PostCode": "ST16 2DH",
            "Country": "ENGLAND"
        }
    },
    "Roles": {
        "Role": [
            {
                "id": "RO222",
                "uniqueRoleId": "247908",
                "primaryRole": "true",
                "Date": {
                    "Type": {
                        "value": "Operational"
                    },
                    "Start": {
                        "value": "2015-04-01"
                    }
                },
                "Status": {
                    "value": "Active"
                }
            }
        ]
    },
    "Rels": {
        "Rel": {
            "id": "RE6",
            "uniqueRelId": "390427",
            "Date": {
                "Type": {
                    "value": "Operational"
                },
                "Start": {
                    "value": "2015-04-01"
                }
            },
            "Status": {
                "value": "Active"
            },
            "Target": {
                "OrgId": {
                    "root": "2.16.840.1.113883.2.1.3.2.4.18.48",
                    "assigningAuthorityName": "HSCIC",
                    "extension": "413"
                },
                "PrimaryRoleId": {
                    "id": "RO141",
                    "uniqueRoleId": "77606"
                }
            }
        }
    },
    "metadata": {
        "org_id": "413AA",
        "status": "Active",
        "role_id": "RO222"
    }
}