{
    "orgRecordClass": "RC1",
    "Name": "SHOREHAM ACADEMY",
    "Date": {
        "Type": {
            "value": "Operational"
        },
        "Start": {
            "value": "2009-09-01"
        }
    },
    "OrgId": {
        "root": "2.16.840.1.113883.2.1.3.2.4.18.48",
        "assigningAuthorityName": "HSCIC",
        "extension": "EE135962"
    },
    "Status": {
        "value": "Active"
    },
    "LastChangeDate": {
        "value": "2023-02-16"
    },
    "GeoLoc": {
        "Location": {
            "AddrLn1": "76 KINGSTON LANE",
            "Town": "SHOREHAM-BY-SEA",
            "PostCode": "BN43 6YT",
            "Country": "ENGLAND",
            "UPRN": "60034781"
        }
    },
    "Contacts": {
        "Contact": {
            "type": "tel",
            "value": "01273 274100"
        }
    },
    "Roles": {
        "Role": [
            {
                "id": "RO221",
                "uniqueRoleId": "443125",
                "primaryRole": "true",
                "Date": {
                    "Type": {
                        "value": "Operational"
                    },
                    "Start": {
                        "value": "2009-09-01"
                    }
                },
                "Status": {
                    "value": "Active"
                }
            },
            {
                "id": "RO297",
                "uniqueRoleId": "443126",
                "Date": {
                    "Type": {
                        "value": "Operational"
                    },
                    "Start": {
                        "value": "2009-09-01"
                    }
                },
                "Status": {
                    "value": "Active"
                }
            }
        ]
    },
    "Rels": {
        "Rel": [
            {
                "id": "RE5",
                "uniqueRelId": "767181",
                "Date": {
                    "Type": {
                        "value": "Operational"
                    },
                    "Start": {
                        "value": "2009-09-01"
                    }
                },
                "Status": {
                    "value": "Active"
                },
                "Target": {
                    "OrgId": {
                        "root": "2.16.840.1.113883.2.1.3.2.4.18.48",
                        "assigningAuthorityName": "HSCIC",
                        "extension": "807"
                    },
                    "PrimaryRoleId": {
                        "id": "RO141",
                        "uniqueRoleId": "99532"
                    }
                }
            },
            {
                "id": "RE5",
                "uniqueRelId": "767180",
                "Date": [
                    {
                        "Type": {
                            "value": "Legal"
                        },
                        "Start": {
                            "value": "2020-04-01"
                        }
                    },
                    {
                        "Type": {
                            "value": "Operational"
                        },
                        "Start": {
                            "value": "2019-10-23"
                        }
                    }
                ],
                "Status": {
                    "value": "Active"
                },
                "Target": {
                    "OrgId": {
                        "root": "2.16.840.1.113883.2.1.3.2.4.18.48",
                        "assigningAuthorityName": "HSCIC",
                        "extension": "70F"
                    },
                    "PrimaryRoleId": {
                        "id": "RO98",
                        "uniqueRoleId": "386493"
                    }
                }
            }
        ]
    },
    "metadata": {
        "org_id": "EE135962",
        "status": "Active",
        "role_id": "RO221",
        "post_code": "BN43 6YT",
        "uprn": "60034781"
    }
}