{
    "orgRecordClass": "RC1",
    "Name": "HOE VALLEY SCHOOL",
    "Date": {
        "Type": {
            "value": "Operational"
        },
        "Start": {
            "value": "2015-09-01"
        }
    },
    "OrgId": {
        "root": "2.16.840.1.113883.2.1.3.2.4.18.48",
        "assigningAuthorityName": "HSCIC",
        "extension": "EE142009"
    },
    "Status": {
        "value": "Active"
    },
    "LastChangeDate": {
        "value": "2023-01-25"
    },
    "GeoLoc": {
        "Location": {
            "AddrLn1": "EGLEY ROAD",
            "Town": "WOKING",
            "PostCode": "GU22 0NH",
            "Country": "ENGLAND",
            "UPRN": "10002427751"
        }
    },
    "Contacts": {
        "Contact": {
            "type": "tel",
            "value": "01483 662627"
        }
    },
    "Roles": {
        "Role": [
            {
                "id": "RO221",
                "uniqueRoleId": "452245",
                "primaryRole": "true",
                "Date": {
                    "Type": {
                        "value": "Operational"
                    },
                    "Start": {
                        "value": "2015-09-01"
                    }
                },
                "Status": {
                    "value": "Active"
                }
            },
            {
                "id": "RO303",
                "uniqueRoleId": "452246",
                "Date": {
                    "Type": {
                        "value": "Operational"
                    },
                    "Start": {
                        "value": "2015-09-01"
                    }
                },
                "Status": {
                    "value": "Active"
                }
            }
        ]
    },
    "Rels": {
        "Rel": [
            {
                "id": "RE5",
                "uniqueRelId": "776342",
                "Date": {
                    "Type": {
                        "value": "Operational"
                    },
                    "Start": {
                        "value": "2015-09-01"
                    }
                },
                "Status": {
                    "value": "Active"
                },
                "Target": {
                    "OrgId": {
                        "root": "2.16.840.1.113883.2.1.3.2.4.18.48",
                        "assigningAuthorityName": "HSCIC",
                        "extension": "805"
                    },
                    "PrimaryRoleId": {
                        "id": "RO141",
                        "uniqueRoleId": "99531"
                    }
                }
            },
            {
                "id": "RE5",
                "uniqueRelId": "776341",
                "Date": [
                    {
                        "Type": {
                            "value": "Legal"
                        },
                        "Start": {
                            "value": "2020-04-01"
                        }
                    },
                    {
                        "Type": {
                            "value": "Operational"
                        },
                        "Start": {
                            "value": "2019-10-23"
                        }
                    }
                ],
                "Status": {
                    "value": "Active"
                },
                "Target": {
                    "OrgId": {
                        "root": "2.16.840.1.113883.2.1.3.2.4.18.48",
                        "assigningAuthorityName": "HSCIC",
                        "extension": "92A"
                    },
                    "PrimaryRoleId": {
                        "id": "RO98",
                        "uniqueRoleId": "386492"
                    }
                }
            }
        ]
    },
    "metadata": {
        "org_id": "EE142009",
        "status": "Active",
        "role_id": "RO221",
        "post_code": "GU22 0NH",
        "uprn": "10002427751"
    }
}