{
    "orgRecordClass": "RC1",
    "Name": "OUR LADY OF THE ASSUMPTION CATHOLIC PRIMARY SCHOOL, BLACKPOOL",
    "Date": {
        "Type": {
            "value": "Operational"
        },
        "Start": {
            "value": "2024-06-01"
        }
    },
    "OrgId": {
        "root": "2.16.840.1.113883.2.1.3.2.4.18.48",
        "assigningAuthorityName": "HSCIC",
        "extension": "EE150866"
    },
    "Status": {
        "value": "Active"
    },
    "LastChangeDate": {
        "value": "2024-07-01"
    },
    "GeoLoc": {
        "Location": {
            "AddrLn1": "COMMON EDGE ROAD",
            "Town": "BLACKPOOL",
            "PostCode": "FY4 5DF",
            "Country": "ENGLAND",
            "UPRN": "100012614461"
        }
    },
    "Contacts": {
        "Contact": {
            "type": "tel",
            "value": "01253 762833"
        }
    },
    "Roles": {
        "Role": [
            {
                "id": "RO221",
                "uniqueRoleId": "527571",
                "primaryRole": "true",
                "Date": {
                    "Type": {
                        "value": "Operational"
                    },
                    "Start": {
                        "value": "2024-06-01"
                    }
                },
                "Status": {
                    "value": "Active"
                }
            },
            {
                "id": "RO302",
                "uniqueRoleId": "527572",
                "Date": {
                    "Type": {
                        "value": "Operational"
                    },
                    "Start": {
                        "value": "2024-06-01"
                    }
                },
                "Status": {
                    "value": "Active"
                }
            }
        ]
    },
    "Rels": {
        "Rel": [
            {
                "id": "RE5",
                "uniqueRelId": "848444",
                "Date": {
                    "Type": {
                        "value": "Operational"
                    },
                    "Start": {
                        "value": "2024-06-01"
                    }
                },
                "Status": {
                    "value": "Active"
                },
                "Target": {
                    "OrgId": {
                        "root": "2.16.840.1.113883.2.1.3.2.4.18.48",
                        "assigningAuthorityName": "HSCIC",
                        "extension": "325"
                    },
                    "PrimaryRoleId": {
                        "id": "RO141",
                        "uniqueRoleId": "77605"
                    }
                }
            },
            {
                "id": "RE5",
                "uniqueRelId": "848443",
                "Date": {
                    "Type": {
                        "value": "Operational"
                    },
                    "Start": {
                        "value": "2024-06-01"
                    }
                },
                "Status": {
                    "value": "Active"
                },
                "Target": {
                    "OrgId": {
                        "root": "2.16.840.1.113883.2.1.3.2.4.18.48",
                        "assigningAuthorityName": "HSCIC",
                        "extension": "00R"
                    },
                    "PrimaryRoleId": {
                        "id": "RO98",
                        "uniqueRoleId": "161400"
                    }
                }
            }
        ]
    },
    "metadata": {
        "org_id": "EE150866",
        "status": "Active",
        "role_id": "RO221",
        "post_code": "FY4 5DF",
        "uprn": "100012614461"
    }
}