{
    "orgRecordClass": "RC1",
    "Name": "R S OAKDEN",
    "Date": {
        "Type": {
            "value": "Operational"
        },
        "Start": {
            "value": "2008-11-25"
        },
        "End": {
            "value": "2022-03-22"
        }
    },
    "OrgId": {
        "root": "2.16.840.1.113883.2.1.3.2.4.18.48",
        "assigningAuthorityName": "HSCIC",
        "extension": "A7VD"
    },
    "Status": {
        "value": "Inactive"
    },
    "LastChangeDate": {
        "value": "2022-04-19"
    },
    "GeoLoc": {
        "Location": {
            "AddrLn1": "39 PENKETT ROAD",
            "AddrLn2": "WALLASEY",
            "Town": "WIRRAL",
            "County": "MERSEYSIDE",
            "PostCode": "CH45 7QF",
            "Country": "ENGLAND"
        }
    },
    "Roles": {
        "Role": {
            "id": "RO104",
            "uniqueRoleId": "241320",
            "primaryRole": "true",
            "Date": {
                "Type": {
                    "value": "Operational"
                },
                "Start": {
                    "value": "2008-11-25"
                },
                "End": {
                    "value": "2022-03-22"
                }
            },
            "Status": {
                "value": "Inactive"
            }
        }
    },
    "metadata": {
        "org_id": "A7VD",
        "status": "Inactive",
        "role_id": "RO104"
    }
}