{
    "orgRecordClass": "RC1",
    "Name": "CARMEL DOMICILIARY CARE LIMITED",
    "Date": {
        "Type": {
            "value": "Operational"
        },
        "Start": {
            "value": "2013-05-17"
        },
        "End": {
            "value": "2021-01-20"
        }
    },
    "OrgId": {
        "root": "2.16.840.1.113883.2.1.3.2.4.18.48",
        "assigningAuthorityName": "HSCIC",
        "extension": "VN0NG"
    },
    "Status": {
        "value": "Inactive"
    },
    "LastChangeDate": {
        "value": "2021-02-12"
    },
    "GeoLoc": {
        "Location": {
            "AddrLn1": "119 OXFORD ROAD",
            "Town": "GLOUCESTER",
            "County": "GLOUCESTERSHIRE",
            "PostCode": "GL1 3ED",
            "Country": "ENGLAND"
        }
    },
    "Roles": {
        "Role": [
            {
                "id": "RO101",
                "uniqueRoleId": "358365",
                "primaryRole": "true",
                "Date": {
                    "Type": {
                        "value": "Operational"
                    },
                    "Start": {
                        "value": "2013-05-17"
                    },
                    "End": {
                        "value": "2021-01-20"
                    }
                },
                "Status": {
                    "value": "Inactive"
                }
            },
            {
                "id": "RO270",
                "uniqueRoleId": "358366",
                "Date": {
                    "Type": {
                        "value": "Operational"
                    },
                    "Start": {
                        "value": "2013-05-17"
                    },
                    "End": {
                        "value": "2021-01-20"
                    }
                },
                "Status": {
                    "value": "Inactive"
                }
            }
        ]
    },
    "Rels": {
        "Rel": [
            {
                "id": "RE5",
                "uniqueRelId": "575961",
                "Date": {
                    "Type": {
                        "value": "Operational"
                    },
                    "Start": {
                        "value": "2013-05-17"
                    },
                    "End": {
                        "value": "2021-01-20"
                    }
                },
                "Status": {
                    "value": "Inactive"
                },
                "Target": {
                    "OrgId": {
                        "root": "2.16.840.1.113883.2.1.3.2.4.18.48",
                        "assigningAuthorityName": "HSCIC",
                        "extension": "11M"
                    },
                    "PrimaryRoleId": {
                        "id": "RO98",
                        "uniqueRoleId": "161521"
                    }
                }
            },
            {
                "id": "RE6",
                "uniqueRelId": "575962",
                "Date": {
                    "Type": {
                        "value": "Operational"
                    },
                    "Start": {
                        "value": "2013-05-17"
                    },
                    "End": {
                        "value": "2021-01-20"
                    }
                },
                "Status": {
                    "value": "Inactive"
                },
                "Target": {
                    "OrgId": {
                        "root": "2.16.840.1.113883.2.1.3.2.4.18.48",
                        "assigningAuthorityName": "HSCIC",
                        "extension": "AQ5L"
                    },
                    "PrimaryRoleId": {
                        "id": "RO104",
                        "uniqueRoleId": "349409"
                    }
                }
            }
        ]
    },
    "metadata": {
        "org_id": "VN0NG",
        "status": "Inactive",
        "role_id": "RO101"
    }
}