{
    "orgRecordClass": "RC1",
    "Name": "SIGNATURE CARE",
    "Date": {
        "Type": {
            "value": "Operational"
        },
        "Start": {
            "value": "2020-12-03"
        },
        "End": {
            "value": "2022-08-03"
        }
    },
    "OrgId": {
        "root": "2.16.840.1.113883.2.1.3.2.4.18.48",
        "assigningAuthorityName": "HSCIC",
        "extension": "VNHCG"
    },
    "Status": {
        "value": "Inactive"
    },
    "LastChangeDate": {
        "value": "2022-08-18"
    },
    "GeoLoc": {
        "Location": {
            "AddrLn1": "HIGHFIELD HOUSE",
            "AddrLn2": "185 CHORLEY NEW ROAD",
            "Town": "BOLTON",
            "PostCode": "BL1 4QZ",
            "Country": "ENGLAND",
            "UPRN": "200002546178"
        }
    },
    "Roles": {
        "Role": [
            {
                "id": "RO101",
                "uniqueRoleId": "405334",
                "primaryRole": "true",
                "Date": {
                    "Type": {
                        "value": "Operational"
                    },
                    "Start": {
                        "value": "2020-12-03"
                    },
                    "End": {
                        "value": "2022-08-03"
                    }
                },
                "Status": {
                    "value": "Inactive"
                }
            },
            {
                "id": "RO270",
                "uniqueRoleId": "405335",
                "Date": {
                    "Type": {
                        "value": "Operational"
                    },
                    "Start": {
                        "value": "2020-12-03"
                    },
                    "End": {
                        "value": "2022-08-03"
                    }
                },
                "Status": {
                    "value": "Inactive"
                }
            }
        ]
    },
    "Rels": {
        "Rel": [
            {
                "id": "RE5",
                "uniqueRelId": "721861",
                "Date": {
                    "Type": {
                        "value": "Operational"
                    },
                    "Start": {
                        "value": "2020-12-03"
                    },
                    "End": {
                        "value": "2022-08-03"
                    }
                },
                "Status": {
                    "value": "Inactive"
                },
                "Target": {
                    "OrgId": {
                        "root": "2.16.840.1.113883.2.1.3.2.4.18.48",
                        "assigningAuthorityName": "HSCIC",
                        "extension": "00T"
                    },
                    "PrimaryRoleId": {
                        "id": "RO98",
                        "uniqueRoleId": "161401"
                    }
                }
            },
            {
                "id": "RE6",
                "uniqueRelId": "721860",
                "Date": {
                    "Type": {
                        "value": "Operational"
                    },
                    "Start": {
                        "value": "2020-12-03"
                    },
                    "End": {
                        "value": "2022-08-03"
                    }
                },
                "Status": {
                    "value": "Inactive"
                },
                "Target": {
                    "OrgId": {
                        "root": "2.16.840.1.113883.2.1.3.2.4.18.48",
                        "assigningAuthorityName": "HSCIC",
                        "extension": "C2DA"
                    },
                    "PrimaryRoleId": {
                        "id": "RO104",
                        "uniqueRoleId": "404884"
                    }
                }
            }
        ]
    },
    "metadata": {
        "org_id": "VNHCG",
        "status": "Inactive",
        "role_id": "RO101"
    }
}