{
    "orgRecordClass": "RC1",
    "Name": "CARE ANGELS BATLY (NEW)",
    "Date": {
        "Type": {
            "value": "Operational"
        },
        "Start": {
            "value": "2023-01-20"
        },
        "End": {
            "value": "2023-03-03"
        }
    },
    "OrgId": {
        "root": "2.16.840.1.113883.2.1.3.2.4.18.48",
        "assigningAuthorityName": "HSCIC",
        "extension": "VNP30"
    },
    "Status": {
        "value": "Inactive"
    },
    "LastChangeDate": {
        "value": "2023-03-16"
    },
    "GeoLoc": {
        "Location": {
            "AddrLn1": "12 CROSS BANK ROAD",
            "Town": "BATLEY",
            "County": "NORFOLK",
            "PostCode": "WF17 8PJ",
            "Country": "ENGLAND"
        }
    },
    "Roles": {
        "Role": [
            {
                "id": "RO101",
                "uniqueRoleId": "497267",
                "primaryRole": "true",
                "Date": {
                    "Type": {
                        "value": "Operational"
                    },
                    "Start": {
                        "value": "2023-01-20"
                    },
                    "End": {
                        "value": "2023-03-03"
                    }
                },
                "Status": {
                    "value": "Inactive"
                }
            },
            {
                "id": "RO270",
                "uniqueRoleId": "497268",
                "Date": {
                    "Type": {
                        "value": "Operational"
                    },
                    "Start": {
                        "value": "2023-01-20"
                    },
                    "End": {
                        "value": "2023-03-03"
                    }
                },
                "Status": {
                    "value": "Inactive"
                }
            }
        ]
    },
    "Rels": {
        "Rel": [
            {
                "id": "RE5",
                "uniqueRelId": "819065",
                "Date": {
                    "Type": {
                        "value": "Operational"
                    },
                    "Start": {
                        "value": "2023-01-20"
                    },
                    "End": {
                        "value": "2023-03-03"
                    }
                },
                "Status": {
                    "value": "Inactive"
                },
                "Target": {
                    "OrgId": {
                        "root": "2.16.840.1.113883.2.1.3.2.4.18.48",
                        "assigningAuthorityName": "HSCIC",
                        "extension": "X2C4Y"
                    },
                    "PrimaryRoleId": {
                        "id": "RO98",
                        "uniqueRoleId": "401261"
                    }
                }
            },
            {
                "id": "RE6",
                "uniqueRelId": "819066",
                "Date": {
                    "Type": {
                        "value": "Operational"
                    },
                    "Start": {
                        "value": "2023-01-20"
                    },
                    "End": {
                        "value": "2023-03-03"
                    }
                },
                "Status": {
                    "value": "Inactive"
                },
                "Target": {
                    "OrgId": {
                        "root": "2.16.840.1.113883.2.1.3.2.4.18.48",
                        "assigningAuthorityName": "HSCIC",
                        "extension": "C5KV"
                    },
                    "PrimaryRoleId": {
                        "id": "RO104",
                        "uniqueRoleId": "496862"
                    }
                }
            }
        ]
    },
    "metadata": {
        "org_id": "VNP30",
        "status": "Inactive",
        "role_id": "RO101"
    }
}